{
  "items": [
    {
      "type": "file",
      "ctime": 1709165198902,
      "path": "Home page.md",
      "title": "Home page"
    },
    {
      "type": "file",
      "ctime": 1709165383474,
      "path": "Roam/david_kudelka_notes/Source page.md",
      "title": "Source page"
    },
    {
      "type": "file",
      "ctime": 1709165396399,
      "path": "Roam/david_kudelka_notes/Work.md",
      "title": "Work"
    },
    {
      "type": "file",
      "ctime": 1709165404854,
      "path": "Roam/david_kudelka_notes/Engineering.md",
      "title": "Engineering"
    },
    {
      "type": "file",
      "ctime": 1709165415946,
      "path": "Roam/david_kudelka_notes/Dogo.md",
      "title": "Dogo"
    },
    {
      "type": "file",
      "ctime": 1709165434497,
      "path": "Roam/david_kudelka_notes/New Car.md",
      "title": "New Car"
    },
    {
      "type": "file",
      "ctime": 1709165449178,
      "path": "Roam/david_kudelka_notes/Home chores.md",
      "title": "Home chores"
    }
  ]
}